{
 "SoundBanksInfo": {
  "Platform": "Mac",
  "BasePlatform": "Mac",
  "SchemaVersion": "12",
  "SoundbankVersion": "135",
  "RootPaths": {
   "ProjectRoot": "E:\\REPOS\\UE_REPOS\\00-ProjectAlpha\\ProjectAlpha\\ProjectAlpha_WwiseProject\\",
   "SourceFilesRoot": "E:\\REPOS\\UE_REPOS\\00-ProjectAlpha\\ProjectAlpha\\ProjectAlpha_WwiseProject\\.cache\\Mac\\",
   "SoundBanksRoot": "E:\\REPOS\\UE_REPOS\\00-ProjectAlpha\\ProjectAlpha\\ProjectAlpha_WwiseProject\\GeneratedSoundBanks\\Mac\\",
   "ExternalSourcesInputFile": "",
   "ExternalSourcesOutputRoot": "E:\\REPOS\\UE_REPOS\\00-ProjectAlpha\\ProjectAlpha\\ProjectAlpha_WwiseProject\\GeneratedSoundBanks\\Mac"
  },
  "SoundBanks": [
   {
    "Id": "4056684167",
    "GUID": "{759BE17C-EAD1-4047-8EF6-C7F4A953DD31}",
    "Language": "SFX",
    "Hash": "1582525304",
    "ObjectPath": "\\SoundBanks\\Default Work Unit\\Master",
    "ShortName": "Master",
    "Path": "Master.bnk",
    "IncludedEvents": [
     {
      "Id": "1866025847",
      "Name": "FootStep",
      "ObjectPath": "\\Events\\Default Work Unit\\MainPlayer\\FootStep",
      "GUID": "{2372179C-C6C2-44B7-8F9E-746DFE9165E3}",
      "MaxAttenuation": "3000.000000",
      "DurationType": "OneShot",
      "DurationMin": "0.192267",
      "DurationMax": "1.533761",
      "IncludedMemoryFiles": [
       {
        "Id": "56716675",
        "Language": "SFX",
        "ShortName": "ESM_War_UI_Source_Hitting_Jagged_Sheet_Metal_With_Hand_5.wav",
        "Path": "SFX\\ESM_War_UI_Source_Hitting_Jagged_Sheet_Metal_With_Hand_5_10C4C929.wem"
       },
       {
        "Id": "248974480",
        "Language": "SFX",
        "ShortName": "ESM_Builder_Game_Footstep_Walk_Stone_3.wav",
        "Path": "SFX\\ESM_Builder_Game_Footstep_Walk_Stone_3_10C4C929.wem"
       },
       {
        "Id": "484107945",
        "Language": "SFX",
        "ShortName": "ESM_War_UI_Source_Hitting_Jagged_Sheet_Metal_With_Hand_3.wav",
        "Path": "SFX\\ESM_War_UI_Source_Hitting_Jagged_Sheet_Metal_With_Hand_3_10C4C929.wem"
       },
       {
        "Id": "636159382",
        "Language": "SFX",
        "ShortName": "ESM_Builder_Game_Footstep_Walk_Stone_2.wav",
        "Path": "SFX\\ESM_Builder_Game_Footstep_Walk_Stone_2_10C4C929.wem"
       },
       {
        "Id": "636893504",
        "Language": "SFX",
        "ShortName": "ESM_War_UI_Source_Hitting_Jagged_Sheet_Metal_With_Hand_1.wav",
        "Path": "SFX\\ESM_War_UI_Source_Hitting_Jagged_Sheet_Metal_With_Hand_1_10C4C929.wem"
       },
       {
        "Id": "653846415",
        "Language": "SFX",
        "ShortName": "ESM_Builder_Game_Footstep_Walk_Stone_6.wav",
        "Path": "SFX\\ESM_Builder_Game_Footstep_Walk_Stone_6_10C4C929.wem"
       },
       {
        "Id": "710239269",
        "Language": "SFX",
        "ShortName": "ESM_War_UI_Source_Hitting_Jagged_Sheet_Metal_With_Hand_8.wav",
        "Path": "SFX\\ESM_War_UI_Source_Hitting_Jagged_Sheet_Metal_With_Hand_8_10C4C929.wem"
       },
       {
        "Id": "752986300",
        "Language": "SFX",
        "ShortName": "ESM_War_UI_Source_Hitting_Jagged_Sheet_Metal_With_Hand_6.wav",
        "Path": "SFX\\ESM_War_UI_Source_Hitting_Jagged_Sheet_Metal_With_Hand_6_10C4C929.wem"
       },
       {
        "Id": "775423440",
        "Language": "SFX",
        "ShortName": "ESM_Builder_Game_Footstep_Walk_Stone_1.wav",
        "Path": "SFX\\ESM_Builder_Game_Footstep_Walk_Stone_1_10C4C929.wem"
       },
       {
        "Id": "965223685",
        "Language": "SFX",
        "ShortName": "ESM_Builder_Game_Footstep_Walk_Stone_4.wav",
        "Path": "SFX\\ESM_Builder_Game_Footstep_Walk_Stone_4_10C4C929.wem"
       },
       {
        "Id": "1001190631",
        "Language": "SFX",
        "ShortName": "ESM_War_UI_Source_Hitting_Jagged_Sheet_Metal_With_Hand_2.wav",
        "Path": "SFX\\ESM_War_UI_Source_Hitting_Jagged_Sheet_Metal_With_Hand_2_10C4C929.wem"
       },
       {
        "Id": "1042562609",
        "Language": "SFX",
        "ShortName": "ESM_Builder_Game_Footstep_Walk_Stone_5.wav",
        "Path": "SFX\\ESM_Builder_Game_Footstep_Walk_Stone_5_10C4C929.wem"
       }
      ],
      "DefaultSwitchValue": "{AF9A5C21-0842-476B-A1A8-6A492814B175}",
      "SwitchContainers": [
       {
        "SwitchValue": "{AF9A5C21-0842-476B-A1A8-6A492814B175}",
        "Media": [
         {
          "Id": "248974480"
         },
         {
          "Id": "636159382"
         },
         {
          "Id": "653846415"
         },
         {
          "Id": "775423440"
         },
         {
          "Id": "965223685"
         },
         {
          "Id": "1042562609"
         }
        ]
       },
       {
        "SwitchValue": "{6F67DACC-4F7E-421E-864B-76864F39BBDD}",
        "Media": [
         {
          "Id": "56716675"
         },
         {
          "Id": "484107945"
         },
         {
          "Id": "636893504"
         },
         {
          "Id": "710239269"
         },
         {
          "Id": "752986300"
         },
         {
          "Id": "1001190631"
         }
        ]
       }
      ]
     },
     {
      "Id": "3797766864",
      "Name": "LightSFX",
      "ObjectPath": "\\Events\\Default Work Unit\\Environment\\LightSFX",
      "GUID": "{7CD0D308-C185-4D8C-AD0C-189AAE6C5B25}",
      "MaxAttenuation": "3000.000000",
      "DurationType": "Infinite",
      "IncludedMemoryFiles": [
       {
        "Id": "1013597397",
        "Language": "SFX",
        "ShortName": "Light02.WAV",
        "Path": "SFX\\Light02_D79FB2B7.wem"
       }
      ]
     },
     {
      "Id": "1022785501",
      "Name": "Snap",
      "ObjectPath": "\\Events\\Default Work Unit\\MainPlayer\\Snap",
      "GUID": "{93FE21DD-CC98-4EA7-91E6-0EB82E09EF19}",
      "DurationType": "OneShot",
      "DurationMin": "0.201370",
      "DurationMax": "0.201370",
      "IncludedMemoryFiles": [
       {
        "Id": "326819284",
        "Language": "SFX",
        "ShortName": "Finger Snap Sound Effect.wav",
        "Path": "SFX\\Finger Snap Sound Effect_BDCE1256.wem"
       }
      ]
     }
    ],
    "GameParameters": [
     {
      "Id": "1685747766",
      "Name": "LowPass",
      "ObjectPath": "\\Game Parameters\\Default Work Unit\\LowPass",
      "GUID": "{5207759D-B96C-450D-B2A0-4107FB2DB6AA}"
     },
     {
      "Id": "4053556705",
      "Name": "AngleAtDoor",
      "ObjectPath": "\\Game Parameters\\Default Work Unit\\AngleAtDoor",
      "GUID": "{DD51276D-1775-45FA-9C14-EFF5CA9E3578}"
     }
    ],
    "SwitchGroups": [
     {
      "Id": "3865314626",
      "Name": "Material",
      "ObjectPath": "\\Switches\\Default Work Unit\\MainPlayer\\Material",
      "GUID": "{E72C5257-77A4-41FF-83F3-EDECABB6577D}",
      "Switches": [
       {
        "Id": "2473969246",
        "Name": "Metal",
        "ObjectPath": "\\Switches\\Default Work Unit\\MainPlayer\\Material\\Metal",
        "GUID": "{6F67DACC-4F7E-421E-864B-76864F39BBDD}"
       },
       {
        "Id": "841620460",
        "Name": "Concrete",
        "ObjectPath": "\\Switches\\Default Work Unit\\MainPlayer\\Material\\Concrete",
        "GUID": "{AF9A5C21-0842-476B-A1A8-6A492814B175}"
       }
      ]
     }
    ]
   }
  ]
 }
}